anime1/__main__.py
anime1-0.1.0.dist-info/METADATA
anime1-0.1.0.dist-info/WHEEL
anime1-0.1.0.dist-info/RECORD
