Metadata-Version: 2.1
Name: anime1
Version: 0.1.0
Summary: CLI access to anime1.me (beta)
License: MIT
Author: evnchn
Author-email: evanchan040511@gmail.com
Requires-Python: >=3.11,<4.0
Classifier: License :: OSI Approved :: MIT License
Classifier: Programming Language :: Python :: 3
Classifier: Programming Language :: Python :: 3.11
Requires-Dist: bs4 (>=0.0.1,<0.0.2)
Requires-Dist: fake-useragent (>=1.1.1,<2.0.0)
Requires-Dist: lxml (>=4.9.2,<5.0.0)
Requires-Dist: pathlib (>=1.0.1,<2.0.0)
Requires-Dist: requests (>=2.28.1,<3.0.0)
